gbc/__init__.py
gbc-0.0.2.dist-info/LICENSE
gbc-0.0.2.dist-info/METADATA
gbc-0.0.2.dist-info/WHEEL
gbc-0.0.2.dist-info/entry_points.txt
gbc-0.0.2.dist-info/RECORD
