Metadata-Version: 2.1
Name: gbc
Version: 0.0.2
Summary: A Python gopher client.
Home-page: https://github.com/gopherball/gbc
License: MIT
Keywords: gopher,proxy
Author: Simon de Vlieger
Author-email: cmdr@supakeen.com
Requires-Python: >=3.9,<4
Classifier: License :: OSI Approved :: MIT License
Classifier: Programming Language :: Python
Classifier: Programming Language :: Python :: 3
Classifier: Programming Language :: Python :: 3.9
Classifier: Programming Language :: Python :: 3.10
Classifier: Programming Language :: Python :: 3.11
Classifier: Programming Language :: Python :: 3
Project-URL: Repository, https://github.com/gopherball/gbc
